sonnenbatterie/__init__.py
sonnenbatterie/const.py
sonnenbatterie/sonnenbatterie.py
sonnenbatterie-0.7.1.dist-info/licenses/LICENSE
sonnenbatterie2/__init__.py
sonnenbatterie2/const.py
sonnenbatterie2/sonnenbatterie2.py
timeofuse/__init__.py
timeofuse/timeofuse.py
sonnenbatterie-0.7.1.dist-info/METADATA
sonnenbatterie-0.7.1.dist-info/WHEEL
sonnenbatterie-0.7.1.dist-info/top_level.txt
sonnenbatterie-0.7.1.dist-info/RECORD
