Metadata-Version: 2.4
Name: sonnenbatterie
Version: 0.7.1
Summary: "Access Sonnenbatterie REST API"
Home-page: https://github.com/weltmeyer/python_sonnenbatterie
Author: Jan Weltmeyer
License: GPLv3
Project-URL: Issue Tracker, https://github.com/weltmeyer/python_sonnenbatterie/issues
Classifier: Development Status :: 4 - Beta
Classifier: Programming Language :: Python :: 3.10
Classifier: Operating System :: OS Independent
Classifier: Environment :: Console
Classifier: License :: OSI Approved :: GNU General Public License v3 (GPLv3)
Requires-Python: >=3.10
License-File: LICENSE
Requires-Dist: requests
Requires-Dist: aiohttp
Dynamic: license-file
